marklogic/__init__.py
marklogic/client.py
marklogic/cloud_auth.py
marklogic/documents.py
marklogic/internal/eval.py
marklogic/internal/util.py
marklogic/rows.py
marklogic/transactions.py
marklogic/vectors.py
marklogic_python_client-1.3.1.dist-info/METADATA
marklogic_python_client-1.3.1.dist-info/WHEEL
marklogic_python_client-1.3.1.dist-info/licenses/LICENSE
marklogic_python_client-1.3.1.dist-info/licenses/NOTICE.txt
marklogic_python_client-1.3.1.dist-info/RECORD
