Metadata-Version: 2.4
Name: marklogic-python-client
Version: 1.3.1
Summary: Python client for MarkLogic, built on the requests library
License: Apache 2.0
License-File: LICENSE
License-File: NOTICE.txt
Author: MarkLogic
Author-email: general@developer.marklogic.com
Requires-Python: >=3.9,<4.0
Classifier: License :: Other/Proprietary License
Classifier: Programming Language :: Python :: 3
Classifier: Programming Language :: Python :: 3.9
Classifier: Programming Language :: Python :: 3.10
Classifier: Programming Language :: Python :: 3.11
Classifier: Programming Language :: Python :: 3.12
Classifier: Programming Language :: Python :: 3.13
Classifier: Programming Language :: Python :: 3.14
Requires-Dist: requests (>=2.32.5,<3.0.0)
Requires-Dist: requests_toolbelt (>=1.0.0,<2.0.0)
Requires-Dist: urllib3 (>=2.6.3,<3.0.0)
